opensubtitles_downloader/__init__.py
opensubtitles_downloader/assembler.py
opensubtitles_downloader/cleaner.py
opensubtitles_downloader/constants.py
opensubtitles_downloader/error_handler.py
opensubtitles_downloader/logger.py
opensubtitles_downloader/opensubtitles_client.py
opensubtitles_downloader/util.py
tests/__init__.py
tests/test_files_correlation.py
tests/test_title_recognise.py
opensubtitles_downloader-1.0.6.dist-info/LICENSE
opensubtitles_downloader-1.0.6.dist-info/METADATA
opensubtitles_downloader-1.0.6.dist-info/WHEEL
opensubtitles_downloader-1.0.6.dist-info/entry_points.txt
opensubtitles_downloader-1.0.6.dist-info/top_level.txt
opensubtitles_downloader-1.0.6.dist-info/RECORD
