Metadata-Version: 2.1
Name: opensubtitles-downloader
Version: 1.0.6
Summary: cli program for subtitles download from OpenSubtitles
Home-page: https://gitlab.com/ubalot/opensubtitles_downloader
Author: ubalot
Author-email: ubalot1@gmail.com
License: GPLv3
Keywords: OpenSubtitles,subtitles,downloader
Platform: UNKNOWN
Requires-Dist: send2trash
